[{"wins": 42.731277533039645, "5.11": {"wins": 227, "picks": 433}, "name": "Aatrox", "5.14": {"wins": 324, "picks": 610}, "picks": 40.87759815242493}, {"wins": 23.853211009174302, "5.11": {"wins": 436, "picks": 858}, "name": "Ahri", "5.14": {"wins": 540, "picks": 1018}, "picks": 18.64801864801864}, {"wins": -0.8849557522123908, "5.11": {"wins": 226, "picks": 464}, "name": "Akali", "5.14": {"wins": 224, "picks": 452}, "picks": -2.5862068965517238}, {"wins": -11.111111111111116, "5.11": {"wins": 351, "picks": 708}, "name": "Alistar", "5.14": {"wins": 312, "picks": 650}, "picks": -8.192090395480223}, {"wins": -27.43362831858407, "5.11": {"wins": 339, "picks": 609}, "name": "Amumu", "5.14": {"wins": 246, "picks": 446}, "picks": -26.76518883415435}, {"wins": 29.41176470588236, "5.11": {"wins": 102, "picks": 211}, "name": "Anivia", "5.14": {"wins": 132, "picks": 271}, "picks": 28.436018957345976}, {"wins": -3.4379671150971625, "5.11": {"wins": 669, "picks": 1303}, "name": "Annie", "5.14": {"wins": 646, "picks": 1280}, "picks": -1.765157329240219}, {"wins": -36.988968202465934, "5.11": {"wins": 1541, "picks": 3039}, "name": "Ashe", "5.14": {"wins": 971, "picks": 1898}, "picks": -37.54524514642975}, {"wins": -0.3048780487804881, "5.11": {"wins": 328, "picks": 745}, "name": "Azir", "5.14": {"wins": 327, "picks": 655}, "picks": -12.080536912751683}, {"wins": -31.780821917808222, "5.11": {"wins": 365, "picks": 790}, "name": "Bard", "5.14": {"wins": 249, "picks": 571}, "picks": -27.721518987341774}, {"wins": 16.242424242424235, "5.11": {"wins": 825, "picks": 1541}, "name": "Blitzcrank", "5.14": {"wins": 959, "picks": 1726}, "picks": 12.005191434133678}, {"wins": 309.09090909090907, "5.11": {"wins": 143, "picks": 286}, "name": "Brand", "5.14": {"wins": 585, "picks": 1114}, "picks": 289.5104895104895}, {"wins": 31.32530120481927, "5.11": {"wins": 249, "picks": 485}, "name": "Braum", "5.14": {"wins": 327, "picks": 592}, "picks": 22.061855670103103}, {"wins": -22.08588957055214, "5.11": {"wins": 163, "picks": 353}, "name": "Cassiopeia", "5.14": {"wins": 127, "picks": 265}, "picks": -24.929178470254953}, {"wins": -8.376963350785338, "5.11": {"wins": 382, "picks": 754}, "name": "Cho'Gath", "5.14": {"wins": 350, "picks": 666}, "picks": -11.671087533156498}, {"wins": 18.53932584269662, "5.11": {"wins": 178, "picks": 357}, "name": "Corki", "5.14": {"wins": 211, "picks": 416}, "picks": 16.526610644257712}, {"wins": 23.98648648648649, "5.11": {"wins": 296, "picks": 588}, "name": "Darius", "5.14": {"wins": 367, "picks": 714}, "picks": 21.42857142857142}, {"wins": 33.22259136212624, "5.11": {"wins": 301, "picks": 565}, "name": "Diana", "5.14": {"wins": 401, "picks": 753}, "picks": 33.27433628318583}, {"wins": -13.27433628318584, "5.11": {"wins": 113, "picks": 238}, "name": "Dr. Mundo", "5.14": {"wins": 98, "picks": 228}, "picks": -4.201680672268903}, {"wins": -16.826923076923073, "5.11": {"wins": 416, "picks": 802}, "name": "Draven", "5.14": {"wins": 346, "picks": 720}, "picks": -10.224438902743138}, {"wins": -83.44305464121132, "5.11": {"wins": 3038, "picks": 6289}, "name": "Ekko", "5.14": {"wins": 503, "picks": 1024}, "picks": -83.71760216250597}, {"wins": 785.4545454545455, "5.11": {"wins": 55, "picks": 154}, "name": "Elise", "5.14": {"wins": 487, "picks": 934}, "picks": 506.49350649350646}, {"wins": -3.157894736842104, "5.11": {"wins": 190, "picks": 439}, "name": "Evelynn", "5.14": {"wins": 184, "picks": 407}, "picks": -7.289293849658318}, {"wins": 37.84977908689249, "5.11": {"wins": 679, "picks": 1381}, "name": "Ezreal", "5.14": {"wins": 936, "picks": 2054}, "picks": 48.732802317161486}, {"wins": -24.630541871921185, "5.11": {"wins": 203, "picks": 434}, "name": "Fiddlesticks", "5.14": {"wins": 153, "picks": 308}, "picks": -29.032258064516125}, {"wins": 8.921933085501866, "5.11": {"wins": 269, "picks": 500}, "name": "Fiora", "5.14": {"wins": 293, "picks": 571}, "picks": 14.19999999999999}, {"wins": 93.05263157894737, "5.11": {"wins": 475, "picks": 883}, "name": "Fizz", "5.14": {"wins": 917, "picks": 1823}, "picks": 106.45526613816534}, {"wins": 50.0, "5.11": {"wins": 38, "picks": 74}, "name": "Galio", "5.14": {"wins": 57, "picks": 109}, "picks": 47.297297297297305}, {"wins": 330.3738317757009, "5.11": {"wins": 214, "picks": 428}, "name": "Gangplank", "5.14": {"wins": 921, "picks": 2070}, "picks": 383.64485981308405}, {"wins": 32.42105263157895, "5.11": {"wins": 475, "picks": 934}, "name": "Garen", "5.14": {"wins": 629, "picks": 1218}, "picks": 30.40685224839401}, {"wins": -3.409090909090906, "5.11": {"wins": 440, "picks": 977}, "name": "Gnar", "5.14": {"wins": 425, "picks": 858}, "picks": -12.18014329580348}, {"wins": -52.39520958083832, "5.11": {"wins": 334, "picks": 636}, "name": "Gragas", "5.14": {"wins": 159, "picks": 371}, "picks": -41.666666666666664}, {"wins": 64.57399103139014, "5.11": {"wins": 446, "picks": 844}, "name": "Graves", "5.14": {"wins": 734, "picks": 1471}, "picks": 74.28909952606635}, {"wins": -26.989619377162633, "5.11": {"wins": 289, "picks": 538}, "name": "Hecarim", "5.14": {"wins": 211, "picks": 406}, "picks": -24.53531598513011}, {"wins": 2.0172910662824117, "5.11": {"wins": 347, "picks": 606}, "name": "Heimerdinger", "5.14": {"wins": 354, "picks": 649}, "picks": 7.095709570957087}, {"wins": -12.129380053908356, "5.11": {"wins": 371, "picks": 763}, "name": "Irelia", "5.14": {"wins": 326, "picks": 641}, "picks": -15.989515072083883}, {"wins": 15.254237288135597, "5.11": {"wins": 295, "picks": 591}, "name": "Janna", "5.14": {"wins": 340, "picks": 654}, "picks": 10.659898477157359}, {"wins": 4.950495049504955, "5.11": {"wins": 202, "picks": 417}, "name": "Jarvan IV", "5.14": {"wins": 212, "picks": 458}, "picks": 9.832134292565954}, {"wins": 44.60227272727273, "5.11": {"wins": 352, "picks": 703}, "name": "Jax", "5.14": {"wins": 509, "picks": 955}, "picks": 35.84637268847794}, {"wins": -10.107334525939182, "5.11": {"wins": 1118, "picks": 2212}, "name": "Jinx", "5.14": {"wins": 1005, "picks": 1955}, "picks": -11.618444846292952}, {"wins": -46.140651801029165, "5.11": {"wins": 583, "picks": 1168}, "name": "Kalista", "5.14": {"wins": 314, "picks": 720}, "picks": -38.35616438356164}, {"wins": -16.509433962264154, "5.11": {"wins": 212, "picks": 410}, "name": "Karma", "5.14": {"wins": 177, "picks": 365}, "picks": -10.97560975609756}, {"wins": -12.871287128712872, "5.11": {"wins": 101, "picks": 179}, "name": "Karthus", "5.14": {"wins": 88, "picks": 172}, "picks": -3.9106145251396662}, {"wins": 78.65168539325842, "5.11": {"wins": 89, "picks": 205}, "name": "Kassadin", "5.14": {"wins": 159, "picks": 399}, "picks": 94.6341463414634}, {"wins": -17.770597738287563, "5.11": {"wins": 619, "picks": 1207}, "name": "Katarina", "5.14": {"wins": 509, "picks": 975}, "picks": -19.221209610604806}, {"wins": 165.94202898550722, "5.11": {"wins": 138, "picks": 282}, "name": "Kayle", "5.14": {"wins": 367, "picks": 703}, "picks": 149.29078014184398}, {"wins": 30.508474576271194, "5.11": {"wins": 118, "picks": 248}, "name": "Kennen", "5.14": {"wins": 154, "picks": 259}, "picks": 4.435483870967749}, {"wins": -32.94930875576036, "5.11": {"wins": 434, "picks": 832}, "name": "Kha'Zix", "5.14": {"wins": 291, "picks": 635}, "picks": -23.677884615384613}, {"wins": 29.14285714285714, "5.11": {"wins": 175, "picks": 357}, "name": "Kog'Maw", "5.14": {"wins": 226, "picks": 455}, "picks": 27.450980392156854}, {"wins": -43.85964912280702, "5.11": {"wins": 399, "picks": 878}, "name": "LeBlanc", "5.14": {"wins": 224, "picks": 524}, "picks": -40.31890660592256}, {"wins": -12.195121951219512, "5.11": {"wins": 779, "picks": 1643}, "name": "Lee Sin", "5.14": {"wins": 684, "picks": 1483}, "picks": -9.738283627510647}, {"wins": -60.717410323709544, "5.11": {"wins": 1143, "picks": 2197}, "name": "Leona", "5.14": {"wins": 449, "picks": 830}, "picks": -62.2212107419208}, {"wins": 0.0, "5.11": {"wins": 108, "picks": 230}, "name": "Lissandra", "5.14": {"wins": 108, "picks": 213}, "picks": -7.391304347826089}, {"wins": -55.76036866359446, "5.11": {"wins": 651, "picks": 1262}, "name": "Lucian", "5.14": {"wins": 288, "picks": 629}, "picks": -50.15847860538827}, {"wins": -10.245901639344257, "5.11": {"wins": 244, "picks": 491}, "name": "Lulu", "5.14": {"wins": 219, "picks": 463}, "picks": -5.702647657841142}, {"wins": -27.142857142857146, "5.11": {"wins": 980, "picks": 2030}, "name": "Lux", "5.14": {"wins": 714, "picks": 1376}, "picks": -32.216748768472904}, {"wins": -31.851851851851855, "5.11": {"wins": 405, "picks": 777}, "name": "Malphite", "5.14": {"wins": 276, "picks": 521}, "picks": -32.947232947232955}, {"wins": 13.513513513513509, "5.11": {"wins": 148, "picks": 294}, "name": "Malzahar", "5.14": {"wins": 168, "picks": 333}, "picks": 13.265306122448983}, {"wins": -6.593406593406592, "5.11": {"wins": 182, "picks": 395}, "name": "Maokai", "5.14": {"wins": 170, "picks": 325}, "picks": -17.721518987341767}, {"wins": 35.6951871657754, "5.11": {"wins": 748, "picks": 1490}, "name": "Master Yi", "5.14": {"wins": 1015, "picks": 1993}, "picks": 33.758389261744966}, {"wins": 254.83870967741936, "5.11": {"wins": 279, "picks": 541}, "name": "Miss Fortune", "5.14": {"wins": 990, "picks": 1918}, "picks": 254.5286506469501}, {"wins": -1.7391304347826098, "5.11": {"wins": 115, "picks": 225}, "name": "Mordekaiser", "5.14": {"wins": 113, "picks": 199}, "picks": -11.555555555555552}, {"wins": -12.287334593572774, "5.11": {"wins": 529, "picks": 1038}, "name": "Morgana", "5.14": {"wins": 464, "picks": 952}, "picks": -8.285163776493254}, {"wins": 91.90283400809716, "5.11": {"wins": 247, "picks": 495}, "name": "Nami", "5.14": {"wins": 474, "picks": 964}, "picks": 94.74747474747475}, {"wins": -34.24460431654677, "5.11": {"wins": 695, "picks": 1385}, "name": "Nasus", "5.14": {"wins": 457, "picks": 867}, "picks": -37.40072202166065}, {"wins": -14.309623430962349, "5.11": {"wins": 1195, "picks": 2375}, "name": "Nautilus", "5.14": {"wins": 1024, "picks": 2000}, "picks": -15.789473684210531}, {"wins": 51.7094017094017, "5.11": {"wins": 468, "picks": 1004}, "name": "Nidalee", "5.14": {"wins": 710, "picks": 1494}, "picks": 48.80478087649402}, {"wins": 58.47457627118644, "5.11": {"wins": 118, "picks": 256}, "name": "Nocturne", "5.14": {"wins": 187, "picks": 356}, "picks": 39.0625}, {"wins": -13.636363636363635, "5.11": {"wins": 286, "picks": 563}, "name": "Nunu", "5.14": {"wins": 247, "picks": 509}, "picks": -9.59147424511545}, {"wins": -62.45210727969348, "5.11": {"wins": 522, "picks": 1104}, "name": "Olaf", "5.14": {"wins": 196, "picks": 404}, "picks": -63.40579710144927}, {"wins": 61.111111111111114, "5.11": {"wins": 162, "picks": 345}, "name": "Orianna", "5.14": {"wins": 261, "picks": 555}, "picks": 60.86956521739131}, {"wins": -24.584717607973417, "5.11": {"wins": 301, "picks": 577}, "name": "Pantheon", "5.14": {"wins": 227, "picks": 480}, "picks": -16.811091854419413}, {"wins": 9.210526315789469, "5.11": {"wins": 76, "picks": 155}, "name": "Poppy", "5.14": {"wins": 83, "picks": 179}, "picks": 15.48387096774193}, {"wins": 39.69072164948453, "5.11": {"wins": 194, "picks": 379}, "name": "Quinn", "5.14": {"wins": 271, "picks": 538}, "picks": 41.95250659630607}, {"wins": -1.6949152542372836, "5.11": {"wins": 118, "picks": 241}, "name": "Rammus", "5.14": {"wins": 116, "picks": 229}, "picks": -4.9792531120331995}, {"wins": -37.43315508021391, "5.11": {"wins": 374, "picks": 749}, "name": "Rek'Sai", "5.14": {"wins": 234, "picks": 530}, "picks": -29.238985313751662}, {"wins": -70.41602465331277, "5.11": {"wins": 649, "picks": 1305}, "name": "Renekton", "5.14": {"wins": 192, "picks": 338}, "picks": -74.09961685823755}, {"wins": 12.23628691983123, "5.11": {"wins": 474, "picks": 959}, "name": "Rengar", "5.14": {"wins": 532, "picks": 1122}, "picks": 16.99687174139728}, {"wins": 58.66454689984102, "5.11": {"wins": 629, "picks": 1329}, "name": "Riven", "5.14": {"wins": 998, "picks": 2049}, "picks": 54.17607223476297}, {"wins": 4.878048780487809, "5.11": {"wins": 164, "picks": 350}, "name": "Rumble", "5.14": {"wins": 172, "picks": 348}, "picks": -0.5714285714285672}, {"wins": -70.57356608478803, "5.11": {"wins": 401, "picks": 826}, "name": "Ryze", "5.14": {"wins": 118, "picks": 281}, "picks": -65.98062953995158}, {"wins": -50.69767441860464, "5.11": {"wins": 215, "picks": 436}, "name": "Sejuani", "5.14": {"wins": 106, "picks": 233}, "picks": -46.55963302752294}, {"wins": -34.56375838926174, "5.11": {"wins": 596, "picks": 1173}, "name": "Shaco", "5.14": {"wins": 390, "picks": 794}, "picks": -32.310315430520035}, {"wins": -6.474820143884896, "5.11": {"wins": 417, "picks": 754}, "name": "Shen", "5.14": {"wins": 390, "picks": 759}, "picks": 0.6631299734747964}, {"wins": 53.846153846153854, "5.11": {"wins": 403, "picks": 749}, "name": "Shyvana", "5.14": {"wins": 620, "picks": 1182}, "picks": 57.810413885180246}, {"wins": 37.000000000000014, "5.11": {"wins": 100, "picks": 221}, "name": "Singed", "5.14": {"wins": 137, "picks": 267}, "picks": 20.814479638009043}, {"wins": -26.506024096385538, "5.11": {"wins": 249, "picks": 463}, "name": "Sion", "5.14": {"wins": 183, "picks": 346}, "picks": -25.269978401727865}, {"wins": -24.934036939313987, "5.11": {"wins": 758, "picks": 1542}, "name": "Sivir", "5.14": {"wins": 569, "picks": 1025}, "picks": -33.527885862516214}, {"wins": -31.57894736842105, "5.11": {"wins": 95, "picks": 198}, "name": "Skarner", "5.14": {"wins": 65, "picks": 141}, "picks": -28.787878787878785}, {"wins": 56.58436213991769, "5.11": {"wins": 486, "picks": 933}, "name": "Sona", "5.14": {"wins": 761, "picks": 1467}, "picks": 57.234726688102896}, {"wins": 14.388489208633093, "5.11": {"wins": 278, "picks": 590}, "name": "Soraka", "5.14": {"wins": 318, "picks": 642}, "picks": 8.813559322033893}, {"wins": 203.3707865168539, "5.11": {"wins": 89, "picks": 173}, "name": "Swain", "5.14": {"wins": 270, "picks": 538}, "picks": 210.98265895953756}, {"wins": 7.317073170731714, "5.11": {"wins": 82, "picks": 174}, "name": "Syndra", "5.14": {"wins": 88, "picks": 219}, "picks": 25.86206896551724}, {"wins": -19.713261648745515, "5.11": {"wins": 279, "picks": 491}, "name": "Talon", "5.14": {"wins": 224, "picks": 433}, "picks": -11.81262729124236}, {"wins": 46.491228070175424, "5.11": {"wins": 114, "picks": 208}, "name": "Taric", "5.14": {"wins": 167, "picks": 340}, "picks": 63.46153846153846}, {"wins": -19.962686567164177, "5.11": {"wins": 1072, "picks": 2091}, "name": "Teemo", "5.14": {"wins": 858, "picks": 1670}, "picks": -20.13390722142515}, {"wins": -10.121107266435992, "5.11": {"wins": 1156, "picks": 2305}, "name": "Thresh", "5.14": {"wins": 1039, "picks": 2066}, "picks": -10.368763557483728}, {"wins": 61.34663341645885, "5.11": {"wins": 401, "picks": 857}, "name": "Tristana", "5.14": {"wins": 647, "picks": 1306}, "picks": 52.39206534422405}, {"wins": 42.85714285714286, "5.11": {"wins": 105, "picks": 209}, "name": "Trundle", "5.14": {"wins": 150, "picks": 280}, "picks": 33.97129186602872}, {"wins": -30.805687203791464, "5.11": {"wins": 633, "picks": 1186}, "name": "Tryndamere", "5.14": {"wins": 438, "picks": 798}, "picks": -32.71500843170321}, {"wins": 211.47540983606555, "5.11": {"wins": 244, "picks": 532}, "name": "Twisted Fate", "5.14": {"wins": 760, "picks": 1548}, "picks": 190.97744360902254}, {"wins": -69.69253294289898, "5.11": {"wins": 683, "picks": 1479}, "name": "Twitch", "5.14": {"wins": 207, "picks": 425}, "picks": -71.26436781609196}, {"wins": 10.722610722610714, "5.11": {"wins": 429, "picks": 831}, "name": "Udyr", "5.14": {"wins": 475, "picks": 934}, "picks": 12.394705174488575}, {"wins": -43.75, "5.11": {"wins": 80, "picks": 182}, "name": "Urgot", "5.14": {"wins": 45, "picks": 101}, "picks": -44.505494505494504}, {"wins": 7.328605200945626, "5.11": {"wins": 423, "picks": 820}, "name": "Varus", "5.14": {"wins": 454, "picks": 855}, "picks": 4.268292682926833}, {"wins": 26.594982078853047, "5.11": {"wins": 1395, "picks": 2723}, "name": "Vayne", "5.14": {"wins": 1766, "picks": 3569}, "picks": 31.068674256334926}, {"wins": 41.57303370786516, "5.11": {"wins": 178, "picks": 401}, "name": "Veigar", "5.14": {"wins": 252, "picks": 514}, "picks": 28.179551122194525}, {"wins": 19.17808219178083, "5.11": {"wins": 146, "picks": 306}, "name": "Vel'Koz", "5.14": {"wins": 174, "picks": 370}, "picks": 20.915032679738555}, {"wins": -30.08849557522124, "5.11": {"wins": 452, "picks": 864}, "name": "Vi", "5.14": {"wins": 316, "picks": 653}, "picks": -24.42129629629629}, {"wins": 98.04878048780488, "5.11": {"wins": 205, "picks": 406}, "name": "Viktor", "5.14": {"wins": 406, "picks": 823}, "picks": 102.70935960591135}, {"wins": -29.76588628762542, "5.11": {"wins": 299, "picks": 627}, "name": "Vladimir", "5.14": {"wins": 210, "picks": 481}, "picks": -23.285486443381174}, {"wins": -29.810298102981026, "5.11": {"wins": 369, "picks": 732}, "name": "Volibear", "5.14": {"wins": 259, "picks": 483}, "picks": -34.01639344262295}, {"wins": 43.84615384615385, "5.11": {"wins": 390, "picks": 770}, "name": "Warwick", "5.14": {"wins": 561, "picks": 1043}, "picks": 35.45454545454545}, {"wins": 6.598984771573613, "5.11": {"wins": 394, "picks": 688}, "name": "Wukong", "5.14": {"wins": 420, "picks": 797}, "picks": 15.843023255813948}, {"wins": -72.88135593220339, "5.11": {"wins": 472, "picks": 1025}, "name": "Xerath", "5.14": {"wins": 128, "picks": 242}, "picks": -76.39024390243902}, {"wins": 22.42152466367713, "5.11": {"wins": 446, "picks": 834}, "name": "Xin Zhao", "5.14": {"wins": 546, "picks": 990}, "picks": 18.705035971223015}, {"wins": 17.665289256198346, "5.11": {"wins": 968, "picks": 1957}, "name": "Yasuo", "5.14": {"wins": 1139, "picks": 2257}, "picks": 15.329586101175273}, {"wins": 23.809523809523814, "5.11": {"wins": 63, "picks": 136}, "name": "Yorick", "5.14": {"wins": 78, "picks": 145}, "picks": 6.617647058823528}, {"wins": 64.9746192893401, "5.11": {"wins": 197, "picks": 404}, "name": "Zac", "5.14": {"wins": 325, "picks": 729}, "picks": 80.44554455445545}, {"wins": 17.719298245614045, "5.11": {"wins": 570, "picks": 1161}, "name": "Zed", "5.14": {"wins": 671, "picks": 1419}, "picks": 22.222222222222232}, {"wins": 2.6666666666666616, "5.11": {"wins": 150, "picks": 302}, "name": "Ziggs", "5.14": {"wins": 154, "picks": 293}, "picks": -2.98013245033113}, {"wins": 2.35294117647058, "5.11": {"wins": 85, "picks": 164}, "name": "Zilean", "5.14": {"wins": 87, "picks": 184}, "picks": 12.195121951219523}, {"wins": 4.90196078431373, "5.11": {"wins": 102, "picks": 195}, "name": "Zyra", "5.14": {"wins": 107, "picks": 236}, "picks": 21.02564102564102}]